README.md
setup.cfg
setup.py
DarkNeurons/Classification.py
DarkNeurons/Dark_Neuron_CNN.py
DarkNeurons/Detection.py
DarkNeurons/Download_Convert_Yolo_Weights.py
DarkNeurons/Model_Training.py
DarkNeurons/Prediction.py
DarkNeurons/Preprocessing_Image.py
DarkNeurons/Train_Utils.py
DarkNeurons/YoloV4.py
DarkNeurons/Yolo_Format.py
DarkNeurons/__init__.py
DarkNeurons/deep_sort_tracking.py
DarkNeurons/deepsort_detection.py
DarkNeurons/deepsort_preprocessing.py
DarkNeurons/freeze_model.py
DarkNeurons/generate_detections.py
DarkNeurons/iou_matching.py
DarkNeurons/kalman_filter.py
DarkNeurons/linear_assignment.py
DarkNeurons/models.py
DarkNeurons/nn_matching.py
DarkNeurons/track.py
DarkNeurons/tracker.py
DarkNeurons/utils.py
DarkNeurons/voc_to_yolo.py
DarkNeurons/web_cam_detect.py
DarkNeurons/yolo.py
DarkNeurons/yolo4_model.py
DarkNeurons/yolo4_utils.py
DarkNeurons/yolo_tracking.py
DarkNeurons.egg-info/PKG-INFO
DarkNeurons.egg-info/SOURCES.txt
DarkNeurons.egg-info/dependency_links.txt
DarkNeurons.egg-info/requires.txt
DarkNeurons.egg-info/top_level.txt