Metadata-Version: 2.1
Name: DarkNeurons
Version: 1.3.9
Summary: A Library for Easy Implementation of Deep learning Techniques
Home-page: https://github.com/Tushar-ml/DarkNeuron
Author: Tushar Goel
Author-email: tgoel219@gmail.com
License: MIT
Download-URL: https://github.com/Tushar-ml/DarkNeuron/archive/v1.3.9.tar.gz
Keywords: Keras,Object_Detection,CNN
Platform: UNKNOWN
Classifier: License :: OSI Approved :: MIT License
Classifier: Programming Language :: Python :: 3.6
Classifier: Programming Language :: Python :: 3.7
Classifier: Programming Language :: Python :: 3
